fastapi_opinionated_socket/__init__.py
fastapi_opinionated_socket/events.py
fastapi_opinionated_socket/helpers.py
fastapi_opinionated_socket/plugin.py
fastapi_opinionated_socket-0.1.0.dist-info/METADATA
fastapi_opinionated_socket-0.1.0.dist-info/WHEEL
fastapi_opinionated_socket-0.1.0.dist-info/RECORD
