Metadata-Version: 2.3
Name: fastapi-opinionated-socket
Version: 0.1.0
Summary: 
Author: Azzarnuji
Author-email: azzarnuzy93@gmail.com
Requires-Python: >=3.12
Classifier: Programming Language :: Python :: 3
Classifier: Programming Language :: Python :: 3.12
Classifier: Programming Language :: Python :: 3.13
Requires-Dist: fastapi-opinionated-core (>=0.1.2,<0.2.0)
Requires-Dist: python-engineio (>=4.12.3,<5.0.0)
Requires-Dist: python-socketio (>=5.14.3,<6.0.0)
